pyflix/README.md
pyflix/__init__.py
pyflix/flix.py
pyflix/proxy.py
pyflix-0.9.dist-info/METADATA
pyflix-0.9.dist-info/WHEEL
pyflix-0.9.dist-info/entry_points.txt
pyflix-0.9.dist-info/top_level.txt
pyflix-0.9.dist-info/RECORD
