Metadata-Version: 2.4
Name: pyflix
Version: 0.9
Summary: Python API for Flix drone
Author-email: Oleg Kalachev <okalachev@gmail.com>
License-Expression: MIT
Project-URL: Homepage, https://github.com/okalachev/flix/tree/master/tools/pyflix
Project-URL: Repository, https://github.com/okalachev/flix
Project-URL: Issues, https://github.com/okalachev/flix/issues
Requires-Python: >=3.8
Requires-Dist: pymavlink
